{
  "lock_version": 0,
  "suppressed": false,
  "title": "This is a test 0",
  "display_string": "This is a test 0",
  "accession_date": "2016-07-26",
  "restrictions_apply": false,
  "access_restrictions": false,
  "use_restrictions": false,
  "created_by": "admin",
  "last_modified_by": "admin",
  "create_time": "2016-07-26T21:15:04Z",
  "system_mtime": "2016-07-26T21:15:04Z",
  "user_mtime": "2016-07-26T21:15:04Z",
  "id_0": "test_2016-07-26 14:15:03",
  "jsonmodel_type": "accession",
  "external_ids": [],
  "related_accessions": [],
  "classifications": [],
  "subjects": [],
  "linked_events": [],
  "extents": [],
  "dates": [],
  "external_documents": [],
  "rights_statements": [],
  "deaccessions": [],
  "related_resources": [],
  "linked_agents": [],
  "instances": [],
  "uri": "/repositories/2/accessions/2",
  "repository": {
    "ref": "/repositories/2"
  }
}
